checkhim/__init__.py
checkhim/__version__.py
checkhim/client.py
checkhim/example.py
checkhim/exceptions.py
checkhim-0.1.0.dist-info/licenses/LICENSE
checkhim-0.1.0.dist-info/METADATA
checkhim-0.1.0.dist-info/WHEEL
checkhim-0.1.0.dist-info/top_level.txt
checkhim-0.1.0.dist-info/RECORD
