Metadata-Version: 2.4
Name: checkhim
Version: 0.1.0
Summary: Python SDK for phone number verification via checkhim.tech
Home-page: https://checkhim.tech
Author: CheckHim Tech
Author-email: CheckHim Tech <opensource@checkhim.tech>
License: MIT License
Requires-Python: >=3.7
License-File: LICENSE
Requires-Dist: requests>=2.25.0
Dynamic: author
Dynamic: home-page
Dynamic: license-file
Dynamic: requires-python
